[
    {
        "id": 1,
        "name": "Immerse into the Falls",
        "duration": 5,
        "rating": 4.5,
        "numberOfReviews": 462,
        "price": 465,
        "image": "./images/tour_001.jpg",
        "description":"Lorem ipsum dolor sit amet, consectetur ipsum dolor sit",
        "location":"Al-Alin, Dubai"

    },
    {
        "id": 2,
        "name": "Helicopter Over the Falls",
        "duration": 8,
        "rating": 3.5,
        "numberOfReviews": 641,
        "price": 385,
        "image": "./images/tour_002.jpg",
        "description":"Lorem ipsum dolor sit amet, consectetur ipsum dolor sit",
        "location":"Al-Alin, Dubai"
    },
    {
        "id": 3,
        "name": "The Falls at Night",
        "duration": 2,
        "rating": 4.5,
        "numberOfReviews": 133,
        "price": 144,
        "image": "./images/tour_003.jpg",
        "description":"Lorem ipsum dolor sit amet, consectetur ipsum dolor sit",
        "location":"Al-Alin, Dubai"
    },
    {
        "id": 4,
        "name": "Immerse into the Falls",
        "duration": 5,
        "rating": 4.5,
        "numberOfReviews": 462,
        "price": 465,
        "image": "./images/tour_004.jpg",
        "description":"Lorem ipsum dolor sit amet, consectetur ipsum dolor sit",
        "location":"Al-Alin, Dubai"
    },
    {
        "id": 4,
        "name": "All Around the World",
        "duration": 5,
        "rating": 4.5,
        "numberOfReviews": 462,
        "price": 465,
        "image": "./images/tour_005.jpg",
        "description":"Lorem ipsum dolor sit amet, consectetur ipsum dolor sit",
        "location":"Al-Alin, Dubai"
    },
    {
        "id": 5,
        "name": "View the Casinos",
        "duration": 5,
        "rating": 4.5,
        "numberOfReviews": 462,
        "price": 465,
        "image": "./images/tour_006.jpg",
        "description":"Lorem ipsum dolor sit amet, consectetur ipsum dolor sit",
        "location":"Al-Alin, Dubai"
    },
    {
        "id": 6,
        "name": "Show me the Magic",
        "duration": 8,
        "rating": 3.5,
        "numberOfReviews": 641,
        "price": 385,
        "image": "./images/tour_007.jpg",
        "description":"Lorem ipsum dolor sit amet, consectetur ipsum dolor sit",
        "location":"Al-Alin, Dubai"
    },
    {
        "id": 7,
        "name": "The Falls at Night",
        "duration": 2,
        "rating": 4.5,
        "numberOfReviews": 133,
        "price": 144,
        "image": "./images/tour_008.jpg",
        "description":"Lorem ipsum dolor sit amet, consectetur ipsum dolor sit",
        "location":"Al-Alin, Dubai"
    },
    {
        "id": 1,
        "name": "Immerse into the Falls",
        "duration": 5,
        "rating": 4.5,
        "numberOfReviews": 462,
        "price": 465,
        "image": "./images/tour_001.jpg",
        "description":"Lorem ipsum dolor sit amet, consectetur ipsum dolor sit",
        "location":"Al-Alin, Dubai"

    },
    {
        "id": 2,
        "name": "Helicopter Over the Falls",
        "duration": 8,
        "rating": 3.5,
        "numberOfReviews": 641,
        "price": 385,
        "image": "./images/tour_002.jpg",
        "description":"Lorem ipsum dolor sit amet, consectetur ipsum dolor sit",
        "location":"Al-Alin, Dubai"
    },
    {
        "id": 3,
        "name": "The Falls at Night",
        "duration": 2,
        "rating": 4.5,
        "numberOfReviews": 133,
        "price": 144,
        "image": "./images/tour_003.jpg",
        "description":"Lorem ipsum dolor sit amet, consectetur ipsum dolor sit",
        "location":"Al-Alin, Dubai"
    },
    {
        "id": 4,
        "name": "Immerse into the Falls",
        "duration": 5,
        "rating": 4.5,
        "numberOfReviews": 462,
        "price": 465,
        "image": "./images/tour_004.jpg",
        "description":"Lorem ipsum dolor sit amet, consectetur ipsum dolor sit",
        "location":"Al-Alin, Dubai"
    },
    {
        "id": 4,
        "name": "All Around the World",
        "duration": 5,
        "rating": 4.5,
        "numberOfReviews": 462,
        "price": 465,
        "image": "./images/tour_005.jpg",
        "description":"Lorem ipsum dolor sit amet, consectetur ipsum dolor sit",
        "location":"Al-Alin, Dubai"
    },
    {
        "id": 5,
        "name": "View the Casinos",
        "duration": 5,
        "rating": 4.5,
        "numberOfReviews": 462,
        "price": 465,
        "image": "./images/tour_006.jpg",
        "description":"Lorem ipsum dolor sit amet, consectetur ipsum dolor sit",
        "location":"Al-Alin, Dubai"
    },
    {
        "id": 6,
        "name": "Show me the Magic",
        "duration": 8,
        "rating": 3.5,
        "numberOfReviews": 641,
        "price": 385,
        "image": "./images/tour_007.jpg",
        "description":"Lorem ipsum dolor sit amet, consectetur ipsum dolor sit",
        "location":"Al-Alin, Dubai"
    },
    {
        "id": 7,
        "name": "The Falls at Night",
        "duration": 2,
        "rating": 4.5,
        "numberOfReviews": 133,
        "price": 144,
        "image": "./images/tour_008.jpg",
        "description":"Lorem ipsum dolor sit amet, consectetur ipsum dolor sit",
        "location":"Al-Alin, Dubai"
    },
    {
        "id": 1,
        "name": "Immerse into the Falls",
        "duration": 5,
        "rating": 4.5,
        "numberOfReviews": 462,
        "price": 465,
        "image": "./images/tour_001.jpg",
        "description":"Lorem ipsum dolor sit amet, consectetur ipsum dolor sit",
        "location":"Al-Alin, Dubai"

    },
    {
        "id": 2,
        "name": "Helicopter Over the Falls",
        "duration": 8,
        "rating": 3.5,
        "numberOfReviews": 641,
        "price": 385,
        "image": "./images/tour_002.jpg",
        "description":"Lorem ipsum dolor sit amet, consectetur ipsum dolor sit",
        "location":"Al-Alin, Dubai"
    },
    {
        "id": 3,
        "name": "The Falls at Night",
        "duration": 2,
        "rating": 4.5,
        "numberOfReviews": 133,
        "price": 144,
        "image": "./images/tour_003.jpg",
        "description":"Lorem ipsum dolor sit amet, consectetur ipsum dolor sit",
        "location":"Al-Alin, Dubai"
    },
    {
        "id": 4,
        "name": "Immerse into the Falls",
        "duration": 5,
        "rating": 4.5,
        "numberOfReviews": 462,
        "price": 465,
        "image": "./images/tour_004.jpg",
        "description":"Lorem ipsum dolor sit amet, consectetur ipsum dolor sit",
        "location":"Al-Alin, Dubai"
    },
    {
        "id": 4,
        "name": "All Around the World",
        "duration": 5,
        "rating": 4.5,
        "numberOfReviews": 462,
        "price": 465,
        "image": "./images/tour_005.jpg",
        "description":"Lorem ipsum dolor sit amet, consectetur ipsum dolor sit",
        "location":"Al-Alin, Dubai"
    },
    {
        "id": 5,
        "name": "View the Casinos",
        "duration": 5,
        "rating": 4.5,
        "numberOfReviews": 462,
        "price": 465,
        "image": "./images/tour_006.jpg",
        "description":"Lorem ipsum dolor sit amet, consectetur ipsum dolor sit",
        "location":"Al-Alin, Dubai"
    },
    {
        "id": 6,
        "name": "Show me the Magic",
        "duration": 8,
        "rating": 3.5,
        "numberOfReviews": 641,
        "price": 385,
        "image": "./images/tour_007.jpg",
        "description":"Lorem ipsum dolor sit amet, consectetur ipsum dolor sit",
        "location":"Al-Alin, Dubai"
    },
    {
        "id": 7,
        "name": "The Falls at Night",
        "duration": 2,
        "rating": 4.5,
        "numberOfReviews": 133,
        "price": 144,
        "image": "./images/tour_008.jpg",
        "description":"Lorem ipsum dolor sit amet, consectetur ipsum dolor sit",
        "location":"Al-Alin, Dubai"
    }
]